mosaik_components/mosaik_pypower/model.py
mosaik_components/mosaik_pypower/mosaik.py
mosaik_components/mosaik_pypower/resource_db.py
mosaik_pypower-0.8.7.dist-info/licenses/AUTHORS.txt
mosaik_pypower-0.8.7.dist-info/licenses/LICENSE.txt
mosaik_pypower-0.8.7.dist-info/METADATA
mosaik_pypower-0.8.7.dist-info/WHEEL
mosaik_pypower-0.8.7.dist-info/entry_points.txt
mosaik_pypower-0.8.7.dist-info/top_level.txt
mosaik_pypower-0.8.7.dist-info/RECORD
