Metadata-Version: 2.4
Name: mosaik-pypower
Version: 0.8.7
Summary: An adapter to use PYPOWER with mosaik.
Author-email: Stefan Scherfke <mosaik@offis.de>
License-Expression: MIT
Requires-Python: >=3.9
License-File: LICENSE.txt
License-File: AUTHORS.txt
Requires-Dist: PYPOWER>=5.1.19
Requires-Dist: mosaik-api-v3<4,>=3.0.12
Requires-Dist: numpy>2
Requires-Dist: scipy>=0.9
Requires-Dist: xlrd<2
Dynamic: license-file
